<?xml version="1.0" encoding="utf-8" ?>
<SnippetCollection>
  <Language Lang="R" Guid="{29C0D8E0-C01C-412B-BEE8-7A7A253A31E6}">
    <SnippetDir>
      <OnOff>On</OnOff>
      <Installed>true</Installed>
      <Locale>1033</Locale>
      <DirPath>Snippets\Files\General\</DirPath>
      <LocalizedName>Snippets</LocalizedName>
    </SnippetDir>
    <SnippetDir>
      <OnOff>On</OnOff>
      <Installed>true</Installed>
      <Locale>1033</Locale>
      <DirPath>Snippets\Files\Base\</DirPath>
      <LocalizedName>Base</LocalizedName>
    </SnippetDir>
    <SnippetDir>
      <OnOff>On</OnOff>
      <Installed>true</Installed>
      <Locale>1033</Locale>
      <DirPath>Snippets\Files\Stats\</DirPath>
      <LocalizedName>Stats</LocalizedName>
    </SnippetDir>
  </Language>
</SnippetCollection>